{
  "123": "D:\\123.mp3",
  "drums for rock": "D:\\1Work\\drums for rock.mp3",
  "lovsng \u0432\u0443\u044c\u0449": "D:\\1Work\\lovsng \u0432\u0443\u044c\u0449.mp3",
  "lovsng": "D:\\1Work\\lovsng.mp3",
  "coldwawe": "D:\\1Work\\Music\\coldwawe.mp3",
  "blood": "D:\\1Work\\Music\\experimental\\8-bit\\blood.mp3",
  "can u feel my heart": "D:\\1Work\\Music\\experimental\\8-bit\\can u feel my heart.mp3",
  "noizy8cit": "D:\\1Work\\Music\\experimental\\8-bit\\noizy8cit.mp3",
  "\u0430\u0442\u043c\u043e\u0441\u0444\u0435\u0440\u0430": "D:\\1Work\\Music\\experimental\\8-bit\\\u0430\u0442\u043c\u043e\u0441\u0444\u0435\u0440\u0430.mp3",
  "\u0432\u0435\u0433\u0430\u0441 \u043b\u0430\u0439\u0442\u0441": "D:\\1Work\\Music\\experimental\\8-bit\\\u0432\u0435\u0433\u0430\u0441 \u043b\u0430\u0439\u0442\u0441.mp3",
  "\u0432\u0438\u043a\u0442\u043e\u0440\u0438\u0443\u0441": "D:\\1Work\\Music\\experimental\\8-bit\\\u0432\u0438\u043a\u0442\u043e\u0440\u0438\u0443\u0441.mp3",
  "\u0434\u0438\u0441\u043e\u0440\u0434\u0435\u0440": "D:\\1Work\\Music\\experimental\\8-bit\\\u0434\u0438\u0441\u043e\u0440\u0434\u0435\u0440.mp3",
  "\u0437\u0435\u0440\u043e2": "D:\\1Work\\Music\\experimental\\8-bit\\\u0437\u0435\u0440\u043e2.mp3",
  "\u043e\u043b \u0437\u044a \u043b\u043e\u043d\u043b\u0438 \u043f\u0438\u043b\u043f": "D:\\1Work\\Music\\experimental\\8-bit\\\u043e\u043b \u0437\u044a \u043b\u043e\u043d\u043b\u0438 \u043f\u0438\u043b\u043f.mp3",
  "\u043e\u043d \u0444\u0430\u0435\u0440": "D:\\1Work\\Music\\experimental\\8-bit\\\u043e\u043d \u0444\u0430\u0435\u0440.mp3",
  "\u0441\u043e\u0443": "D:\\1Work\\Music\\experimental\\8-bit\\\u0441\u043e\u0443.mp3",
  "\u0442\u0440\u0438 \u043f\u043e\u043b\u043e\u0441\u043a\u0438": "D:\\1Work\\Music\\experimental\\8-bit\\\u0442\u0440\u0438 \u043f\u043e\u043b\u043e\u0441\u043a\u0438.mp3",
  "anx mastering 2": "D:\\1Work\\Music\\experimental\\anx mastering 2.mp3",
  "anxiety": "D:\\1Work\\Music\\experimental\\anxiety.mp3",
  "call my name": "D:\\1Work\\Music\\experimental\\call my name.mp3",
  "call my name2": "D:\\1Work\\Music\\experimental\\call my name2.mp3",
  "first elgit try": "D:\\1Work\\Music\\experimental\\first elgit try.mp3",
  "hardbass": "D:\\1Work\\Music\\experimental\\hardbass.mp3",
  "He-man - HEYYEYAAEYAAAEYAEYAA(\u043d\u0430\u0439\u0442\u043a\u043e\u0440)": "D:\\1Work\\Music\\experimental\\He-man - HEYYEYAAEYAAAEYAEYAA(\u043d\u0430\u0439\u0442\u043a\u043e\u0440).mp3",
  "holding hands mastered": "D:\\1Work\\Music\\experimental\\holding hands mastered.mp3",
  "Back to the city (Instrumental of Gero\u0438)": "D:\\1Work\\Music\\experimental\\ignikulus \u0438 \u0434\u0440\u0443\u0433\u0430\u044f \u0434\u0438\u0447\u044c\\Bonus Ducks [EP]\\Back to the city (Instrumental of Gero\u0438).mp3",
  "G\u0435r\u043e\u0438 \u044dt\u043e\u0439 w\u043e\u0439\u043d\u044b": "D:\\1Work\\Music\\experimental\\ignikulus \u0438 \u0434\u0440\u0443\u0433\u0430\u044f \u0434\u0438\u0447\u044c\\Bonus Ducks [EP]\\G\u0435r\u043e\u0438 \u044dt\u043e\u0439 w\u043e\u0439\u043d\u044b.mp3",
  "Jordon the Duck": "D:\\1Work\\Music\\experimental\\ignikulus \u0438 \u0434\u0440\u0443\u0433\u0430\u044f \u0434\u0438\u0447\u044c\\Bonus Ducks [EP]\\Jordon the Duck.mp3",
  "Church trap": "D:\\1Work\\Music\\experimental\\ignikulus \u0438 \u0434\u0440\u0443\u0433\u0430\u044f \u0434\u0438\u0447\u044c\\Goose Prophet\\Church trap.mp3",
  "Goose Prophet": "D:\\1Work\\Music\\experimental\\ignikulus \u0438 \u0434\u0440\u0443\u0433\u0430\u044f \u0434\u0438\u0447\u044c\\Goose Prophet\\Goose Prophet.mp3",
  "Innocence Is Bliss": "D:\\1Work\\Music\\experimental\\ignikulus \u0438 \u0434\u0440\u0443\u0433\u0430\u044f \u0434\u0438\u0447\u044c\\Goose Prophet\\Innocence Is Bliss.mp3",
  "Church Trap (Instrumental)": "D:\\1Work\\Music\\experimental\\ignikulus \u0438 \u0434\u0440\u0443\u0433\u0430\u044f \u0434\u0438\u0447\u044c\\Goose Prophet\\Instrumentals\\Church Trap (Instrumental).mp3",
  "goose prophet (Instrumental)": "D:\\1Work\\Music\\experimental\\ignikulus \u0438 \u0434\u0440\u0443\u0433\u0430\u044f \u0434\u0438\u0447\u044c\\Goose Prophet\\Instrumentals\\goose prophet (Instrumental).mp3",
  "MassON (Instrumental)": "D:\\1Work\\Music\\experimental\\ignikulus \u0438 \u0434\u0440\u0443\u0433\u0430\u044f \u0434\u0438\u0447\u044c\\Goose Prophet\\Instrumentals\\MassON (Instrumental).mp3",
  "West up Generation (instrumental)": "D:\\1Work\\Music\\experimental\\ignikulus \u0438 \u0434\u0440\u0443\u0433\u0430\u044f \u0434\u0438\u0447\u044c\\Goose Prophet\\Instrumentals\\West up Generation (instrumental).mp3",
  "Introduction": "D:\\1Work\\Music\\experimental\\ignikulus \u0438 \u0434\u0440\u0443\u0433\u0430\u044f \u0434\u0438\u0447\u044c\\Goose Prophet\\Introduction.mp3",
  "MassON": "D:\\1Work\\Music\\experimental\\ignikulus \u0438 \u0434\u0440\u0443\u0433\u0430\u044f \u0434\u0438\u0447\u044c\\Goose Prophet\\MassON.mp3",
  "West up Generation": "D:\\1Work\\Music\\experimental\\ignikulus \u0438 \u0434\u0440\u0443\u0433\u0430\u044f \u0434\u0438\u0447\u044c\\Goose Prophet\\West up Generation.mp3",
  "Ignikulus - Open Space": "D:\\1Work\\Music\\experimental\\ignikulus \u0438 \u0434\u0440\u0443\u0433\u0430\u044f \u0434\u0438\u0447\u044c\\Ignikulus - Open Space.mp3",
  "\u041c\u0421 \u0416\u043e\u0440\u0438\u043a feat": "D:\\1Work\\Music\\experimental\\ignikulus \u0438 \u0434\u0440\u0443\u0433\u0430\u044f \u0434\u0438\u0447\u044c\\\u041c\u0421 \u0416\u043e\u0440\u0438\u043a feat. \u041c\u0421 \u0424\u0435\u0434\u044f - \u0442\u043e\u043f \u0442\u0440\u0435\u043a.mp3",
  "Hey,Naggi": "D:\\1Work\\Music\\experimental\\ignikulus \u0438 \u0434\u0440\u0443\u0433\u0430\u044f \u0434\u0438\u0447\u044c\\\u041es\u044c\u043c\u0438\u043d\u0430\u0433\\Hey,Naggi.mp3",
  "Igniculus - Dr\u044b\u043d\u0445 Theme": "D:\\1Work\\Music\\experimental\\ignikulus \u0438 \u0434\u0440\u0443\u0433\u0430\u044f \u0434\u0438\u0447\u044c\\\u041es\u044c\u043c\u0438\u043d\u0430\u0433\\Igniculus - Dr\u044b\u043d\u0445 Theme.mp3",
  "Ignikulus - \u0419\u043e\u0443,Gor\u044f\u0447\u0451!": "D:\\1Work\\Music\\experimental\\ignikulus \u0438 \u0434\u0440\u0443\u0433\u0430\u044f \u0434\u0438\u0447\u044c\\\u041es\u044c\u043c\u0438\u043d\u0430\u0433\\Ignikulus - \u0419\u043e\u0443,Gor\u044f\u0447\u0451!.mp3",
  "Ignikulus feat": "D:\\1Work\\Music\\experimental\\ignikulus \u0438 \u0434\u0440\u0443\u0433\u0430\u044f \u0434\u0438\u0447\u044c\\\u041es\u044c\u043c\u0438\u043d\u0430\u0433\\Ignikulus feat.GoogleDj \u2013 \u2020Pr\u0398\u20a3It\u2020.mp3",
  "Ignikulus-l'RA na Leto": "D:\\1Work\\Music\\experimental\\ignikulus \u0438 \u0434\u0440\u0443\u0433\u0430\u044f \u0434\u0438\u0447\u044c\\\u041es\u044c\u043c\u0438\u043d\u0430\u0433\\Ignikulus-l'RA na Leto.mp3",
  "Hey,Naggi (Instrumental)": "D:\\1Work\\Music\\experimental\\ignikulus \u0438 \u0434\u0440\u0443\u0433\u0430\u044f \u0434\u0438\u0447\u044c\\\u041es\u044c\u043c\u0438\u043d\u0430\u0433\\Instrumentals\\Hey,Naggi (Instrumental).mp3",
  "Ignikulus - Dr\u044b\u043d\u0445 Theme (Instrumental)": "D:\\1Work\\Music\\experimental\\ignikulus \u0438 \u0434\u0440\u0443\u0433\u0430\u044f \u0434\u0438\u0447\u044c\\\u041es\u044c\u043c\u0438\u043d\u0430\u0433\\Instrumentals\\Ignikulus - Dr\u044b\u043d\u0445 Theme (Instrumental).mp3",
  "Ignikulus - \u0419\u043e\u0443,Gor\u044f\u0447\u0451! (Instrumental)": "D:\\1Work\\Music\\experimental\\ignikulus \u0438 \u0434\u0440\u0443\u0433\u0430\u044f \u0434\u0438\u0447\u044c\\\u041es\u044c\u043c\u0438\u043d\u0430\u0433\\Instrumentals\\Ignikulus - \u0419\u043e\u0443,Gor\u044f\u0447\u0451! (Instrumental).mp3",
  "l'RA na Leto (Instrumental)": "D:\\1Work\\Music\\experimental\\ignikulus \u0438 \u0434\u0440\u0443\u0433\u0430\u044f \u0434\u0438\u0447\u044c\\\u041es\u044c\u043c\u0438\u043d\u0430\u0433\\Instrumentals\\l'RA na Leto (Instrumental).mp3",
  "PrOfit (Instrumental)": "D:\\1Work\\Music\\experimental\\ignikulus \u0438 \u0434\u0440\u0443\u0433\u0430\u044f \u0434\u0438\u0447\u044c\\\u041es\u044c\u043c\u0438\u043d\u0430\u0433\\Instrumentals\\PrOfit (Instrumental).mp3",
  "\u043a\u043e\u0433\u0434\u0430 \u0441\u0443\u043d \u0438\u0434\u0435\u0442 \u0432\u043d\u0438\u0437 (Instrumental)": "D:\\1Work\\Music\\experimental\\ignikulus \u0438 \u0434\u0440\u0443\u0433\u0430\u044f \u0434\u0438\u0447\u044c\\\u041es\u044c\u043c\u0438\u043d\u0430\u0433\\Instrumentals\\\u043a\u043e\u0433\u0434\u0430 \u0441\u0443\u043d \u0438\u0434\u0435\u0442 \u0432\u043d\u0438\u0437 (Instrumental).mp3",
  "\u043a\u043e\u0433\u0434\u0430 \u0441\u0443\u043d \u0438\u0434\u0435\u0442 \u0432\u043d\u0438\u0437": "D:\\1Work\\Music\\experimental\\ignikulus \u0438 \u0434\u0440\u0443\u0433\u0430\u044f \u0434\u0438\u0447\u044c\\\u041es\u044c\u043c\u0438\u043d\u0430\u0433\\\u043a\u043e\u0433\u0434\u0430 \u0441\u0443\u043d \u0438\u0434\u0435\u0442 \u0432\u043d\u0438\u0437.mp3",
  "\u041d\u043e\u0432\u043e\u0433\u043e\u0434": "D:\\1Work\\Music\\experimental\\ignikulus \u0438 \u0434\u0440\u0443\u0433\u0430\u044f \u0434\u0438\u0447\u044c\\\u041es\u044c\u043c\u0438\u043d\u0430\u0433\\\u041d\u043e\u0432\u043e\u0433\u043e\u0434.mp3",
  "imhere": "D:\\1Work\\Music\\experimental\\imhere.mp3",
  "lofi anxiety": "D:\\1Work\\Music\\experimental\\lofi anxiety.mp3",
  "lofi house mastered": "D:\\1Work\\Music\\experimental\\lofi house mastered.mp3",
  "lofi house stop things": "D:\\1Work\\Music\\experimental\\lofi house stop things.mp3",
  "Ignite - 123": "D:\\1Work\\Music\\experimental\\MC Taras\\Ignite - 123.mp3",
  "Ignite - 123321": "D:\\1Work\\Music\\experimental\\MC Taras\\Ignite - 123321.mp3",
  "Ignite - 512": "D:\\1Work\\Music\\experimental\\MC Taras\\Ignite - 512.mp3",
  "Ignite - Untitled": "D:\\1Work\\Music\\experimental\\MC Taras\\Ignite - Untitled.mp3",
  "Ignite - \u0437\u0430\u0431\u0443\u0432 \u0449\u043e \u0431\u0443\u0432 (inst)": "D:\\1Work\\Music\\experimental\\MC Taras\\Ignite - \u0437\u0430\u0431\u0443\u0432 \u0449\u043e \u0431\u0443\u0432 (inst).mp3",
  "\u0431\u0443\u0434\u0435\u0442\u0435 \u043f\u0440\u0430\u0446\u044e\u0432\u0430\u0442\u0438 (\u0438\u043d\u0441\u0442)": "D:\\1Work\\Music\\experimental\\MC Taras\\\u0431\u0443\u0434\u0435\u0442\u0435 \u043f\u0440\u0430\u0446\u044e\u0432\u0430\u0442\u0438 (\u0438\u043d\u0441\u0442).mp3",
  "\u0431\u0443\u0434\u0435\u0442\u0435": "D:\\1Work\\Music\\experimental\\MC Taras\\\u0431\u0443\u0434\u0435\u0442\u0435.mp3",
  "\u0434\u043e\u0447\u0435\u0440\u0433\u043e\u0432\u0443\u0454": "D:\\1Work\\Music\\experimental\\MC Taras\\\u0434\u043e\u0447\u0435\u0440\u0433\u043e\u0432\u0443\u0454.mp3",
  "\u0434\u043e\u0447\u0435\u0440\u0433\u043e\u0432\u0443\u0435 (\u0438\u043d\u0441\u0442)": "D:\\1Work\\Music\\experimental\\MC Taras\\\u0434\u043e\u0447\u0435\u0440\u0433\u043e\u0432\u0443\u0435 (\u0438\u043d\u0441\u0442).mp3",
  "\u043a\u0437 (\u0438\u043d\u0441)": "D:\\1Work\\Music\\experimental\\MC Taras\\\u043a\u0437 (\u0438\u043d\u0441).mp3",
  "\u041a\u043e\u043d\u0442\u0440\u043e\u043b\u044c\u043d\u0456 \u0437\u0430\u043f\u0438\u0442\u0430\u043d\u043d\u044f": "D:\\1Work\\Music\\experimental\\MC Taras\\\u041a\u043e\u043d\u0442\u0440\u043e\u043b\u044c\u043d\u0456 \u0437\u0430\u043f\u0438\u0442\u0430\u043d\u043d\u044f.mp3",
  "\u043a\u043e\u0441\u0442\u0438\u043d\u0433 (online-audio-converter": "D:\\1Work\\Music\\experimental\\MC Taras\\\u043a\u043e\u0441\u0442\u0438\u043d\u0433 (online-audio-converter.com).mp3",
  "\u043d\u0456\u0447\u043e \u0436 \u043d\u0435 \u0437\u043c\u0456\u043d\u0438\u0442\u044c\u0441\u044f": "D:\\1Work\\Music\\experimental\\MC Taras\\\u043d\u0456\u0447\u043e \u0436 \u043d\u0435 \u0437\u043c\u0456\u043d\u0438\u0442\u044c\u0441\u044f.mp3",
  "\u043d\u0435 \u0441\u043b\u043e\u0436\u043d\u0430 \u0437\u0430\u0434\u0430\u0447\u0430  (\u0438\u043d\u0441\u0442)": "D:\\1Work\\Music\\experimental\\MC Taras\\\u043d\u0435 \u0441\u043b\u043e\u0436\u043d\u0430 \u0437\u0430\u0434\u0430\u0447\u0430  (\u0438\u043d\u0441\u0442).mp3",
  "\u043d\u043e\u0432\u0456\u0439 \u0442\u0440\u0435\u043a": "D:\\1Work\\Music\\experimental\\MC Taras\\\u043d\u043e\u0432\u0456\u0439 \u0442\u0440\u0435\u043a.mp3",
  "\u0440\u0430\u0434\u0456\u0443\u0441 \u043e\u0440\u0431\u0456\u0442\u0438 \u0441\u0443\u043f\u0443\u0442\u043d\u0438\u043a\u0430": "D:\\1Work\\Music\\experimental\\MC Taras\\\u0440\u0430\u0434\u0456\u0443\u0441 \u043e\u0440\u0431\u0456\u0442\u0438 \u0441\u0443\u043f\u0443\u0442\u043d\u0438\u043a\u0430.mp3",
  "\u0442\u0456\u043b\u043e \u0432\u0456\u043b\u044c\u043d\u043e \u043f\u0430\u0434\u0430\u0454 (Instrumental)": "D:\\1Work\\Music\\experimental\\MC Taras\\\u0442\u0456\u043b\u043e \u0432\u0456\u043b\u044c\u043d\u043e \u043f\u0430\u0434\u0430\u0454 (Instrumental).mp3",
  "\u0442\u0456\u043b\u043e \u0432\u0456\u043b\u044c\u043d\u043e \u043f\u0430\u0434\u0430\u0454": "D:\\1Work\\Music\\experimental\\MC Taras\\\u0442\u0456\u043b\u043e \u0432\u0456\u043b\u044c\u043d\u043e \u043f\u0430\u0434\u0430\u0454.mp3",
  "\u0442\u043e\u043f\u043e\u0432\u044b\u0439 \u0433\u0430\u0439\u0434": "D:\\1Work\\Music\\experimental\\MC Taras\\\u0442\u043e\u043f\u043e\u0432\u044b\u0439 \u0433\u0430\u0439\u0434.mp3",
  "\u0446\u0435 \u043d\u0435 \u0441\u043b\u043e\u0436\u043d\u0430 \u0437\u0430\u0434\u0430\u0447\u0430": "D:\\1Work\\Music\\experimental\\MC Taras\\\u0446\u0435 \u043d\u0435 \u0441\u043b\u043e\u0436\u043d\u0430 \u0437\u0430\u0434\u0430\u0447\u0430.mp3",
  "\u0447\u043e\u0440\u043d\u0438 \u0434\u0438\u0440\u044b": "D:\\1Work\\Music\\experimental\\MC Taras\\\u0447\u043e\u0440\u043d\u0438 \u0434\u0438\u0440\u044b.mp3",
  "MITOL demo": "D:\\1Work\\Music\\experimental\\MITOL demo.mp3",
  "night pursit": "D:\\1Work\\Music\\experimental\\night pursit.mp3",
  "synthhouse": "D:\\1Work\\Music\\experimental\\synthhouse.mp3",
  "tame try": "D:\\1Work\\Music\\experimental\\tame try.mp3",
  "\u043a\u0440\u043e\u043b\u043b_\u043c\u0430\u0439\u044f\u043c\u0438": "D:\\1Work\\Music\\experimental\\\u043a\u0440\u043e\u043b\u043b_\u043c\u0430\u0439\u044f\u043c\u0438.mp3",
  "garfield in a box": "D:\\1Work\\Music\\experimental\\\u043c\u044d\u0448\u0430\u043f\\garfield in a box.mp3",
  "heavy dirty woods": "D:\\1Work\\Music\\experimental\\\u043c\u044d\u0448\u0430\u043f\\heavy dirty woods.mp3",
  "hthmolly": "D:\\1Work\\Music\\experimental\\\u043c\u044d\u0448\u0430\u043f\\hthmolly.mp3",
  "\u0454\u043c\u0438\u043d\u0435\u043c \u0445\u0438\u043c\u043c": "D:\\1Work\\Music\\experimental\\\u043c\u044d\u0448\u0430\u043f\\\u0454\u043c\u0438\u043d\u0435\u043c \u0445\u0438\u043c\u043c.mp3",
  "\u043f\u0443\u0442\u0438\u0441": "D:\\1Work\\Music\\experimental\\\u043c\u044d\u0448\u0430\u043f\\\u043f\u0443\u0442\u0438\u0441.mp3",
  "\u043d\u044c\u044e\u0432\u0454\u0439\u0432": "D:\\1Work\\Music\\experimental\\\u043d\u044c\u044e\u0432\u0454\u0439\u0432.mp3",
  "\u043f\u0448\u0438\u0448\u043b\u043e\u0448\u044c\u0449": "D:\\1Work\\Music\\experimental\\\u043f\u0448\u0438\u0448\u043b\u043e\u0448\u044c\u0449.mp3",
  "into witches house": "D:\\1Work\\Music\\himowari\\2018\\into witches house.mp3",
  "suicidal": "D:\\1Work\\Music\\himowari\\2018\\suicidal.mp3",
  "universe": "D:\\1Work\\Music\\himowari\\2018\\universe.mp3",
  "white": "D:\\1Work\\Music\\himowari\\2018\\white.mp3",
  "\u0432\u0430\u043f\u0430\u0440_2 (online-audio-converter": "D:\\1Work\\Music\\himowari\\2018\\\u0432\u0430\u043f\u0430\u0440_2 (online-audio-converter.com).mp3",
  "4564564456": "D:\\1Work\\\u0424\u043e\u0442\u043e\\4564564456.mp3",
  "BPD": "D:\\1Work\\Music\\himowari\\BPD.mp3",
  "bpd2": "D:\\1Work\\Music\\himowari\\bpd2.mp3",
  "for whatever it goes": "D:\\1Work\\Music\\himowari\\is leave possible\\for whatever it goes.mp3",
  "\u043b\u043e\u0443\u0431\u0430\u0441\u0441\u043d\u043e\u043c\u0435\u04402": "D:\\1Work\\Music\\himowari\\is leave possible\\\u043b\u043e\u0443\u0431\u0430\u0441\u0441\u043d\u043e\u043c\u0435\u04402.mp3",
  "new song": "D:\\1Work\\Music\\himowari\\new song.mp3",
  "512\u043b\u0435\u0431\u0430": "D:\\1Work\\Music\\himowari\\super old and shitty stuff\\512\u043b\u0435\u0431\u0430.mp3",
  "almost a christmas song": "D:\\1Work\\Music\\himowari\\super old and shitty stuff\\almost a christmas song.mp3",
  "go daft": "D:\\1Work\\Music\\himowari\\super old and shitty stuff\\go daft.mp3",
  "samokontrol": "D:\\1Work\\Music\\himowari\\super old and shitty stuff\\samokontrol.mp3",
  "shadows hide behind": "D:\\1Work\\Music\\himowari\\super old and shitty stuff\\shadows hide behind.mp3",
  "\u0433\u0430\u043b\u043b\u043e\u0432": "D:\\1Work\\Music\\himowari\\super old and shitty stuff\\\u0433\u0430\u043b\u043b\u043e\u0432.mp3",
  "\u043a\u043e\u0441\u043c \u043f\u044b\u043b\u044c (\u0438\u043d\u0441\u0442)": "D:\\1Work\\Music\\himowari\\super old and shitty stuff\\\u043a\u043e\u0441\u043c \u043f\u044b\u043b\u044c (\u0438\u043d\u0441\u0442).mp3",
  "\u043a\u043e\u0441\u043c\u0438\u0447\u0435\u0441\u043a\u0430\u044f \u043f\u044b\u043b\u044c": "D:\\1Work\\Music\\himowari\\super old and shitty stuff\\\u043a\u043e\u0441\u043c\u0438\u0447\u0435\u0441\u043a\u0430\u044f \u043f\u044b\u043b\u044c.mp3",
  "\u043b\u0435\u0431\u0430\u043d\u043e\u043d": "D:\\1Work\\Music\\himowari\\super old and shitty stuff\\\u043b\u0435\u0431\u0430\u043d\u043e\u043d.mp3",
  "\u043f\u0435\u0440\u0432\u0456\u0439 \u0442\u0440\u0435\u043a": "D:\\1Work\\Music\\himowari\\super old and shitty stuff\\\u043f\u0435\u0440\u0432\u0456\u0439 \u0442\u0440\u0435\u043a.mp3",
  "\u0441\u0430\u043c\u043e\u043a\u043e\u043d\u0442\u0440\u043e\u043b\u044c": "D:\\1Work\\Music\\himowari\\super old and shitty stuff\\\u0441\u0430\u043c\u043e\u043a\u043e\u043d\u0442\u0440\u043e\u043b\u044c.mp3",
  "ultraviolence": "D:\\1Work\\Music\\himowari\\ultraviolence.mp3",
  "sleepwalking september": "D:\\1Work\\Music\\himowari\\\u0432\u0438\u0447\u0443\u0445\u0430\\sleepwalking september.mp3",
  "post punk dynamics": "D:\\1Work\\Music\\post punk dynamics.mp3",
  "summer bass demo": "D:\\1Work\\Music\\summer bass demo.mp3",
  "the better": "D:\\1Work\\\u0424\u043e\u0442\u043e\\the better.mp3",
  "funky demo": "D:\\1Work\\Music\\weather\\1EP houses and homes\\funky demo.mp3",
  "lilll": "D:\\1Work\\Music\\weather\\lilll.mp3",
  "tree house": "D:\\1Work\\Music\\weather\\1EP houses and homes\\tree house.mp3",
  "\u0435\u0449\u0435 \u043e\u0434\u0438\u043d \u0434\u0435\u043d\u044c": "D:\\1Work\\Music\\weather\\\u0435\u0449\u0435 \u043e\u0434\u0438\u043d \u0434\u0435\u043d\u044c.mp3",
  "adorable": "D:\\1Work\\Music\\weather\\adorable.mp3",
  "best friend": "D:\\1Work\\Music\\weather\\best friend.mp3",
  "cold wave demo": "D:\\1Work\\Music\\weather\\cold wave demo.mp3",
  "cold wave dm v2": "D:\\1Work\\Music\\weather\\cold wave dm v2.mp3",
  "czarny kotek": "D:\\1Work\\Music\\weather\\czarny kotek.mp3",
  "distanced": "D:\\1Work\\Music\\weather\\distanced.mp3",
  "do u feel cold demo 2": "D:\\1Work\\Music\\weather\\do u feel cold demo 2.mp3",
  "do u feel cold ver 2": "D:\\1Work\\Music\\weather\\do u feel cold ver 2.mp3",
  "first indie demo": "D:\\1Work\\Music\\weather\\first indie demo.mp3",
  "lost and tired": "D:\\1Work\\Music\\weather\\lost and tired.mp3",
  "missing something": "D:\\1Work\\Music\\weather\\missing something.mp3",
  "v2 mastered": "D:\\1Work\\Music\\weather\\v2 mastered.mp3",
  "2": "D:\\1Work\\Music\\\u043f\u0430\u043f\u043a\u0438 \u0441 \u0434\u0435\u043c\u043a\u0430\u043c\u0438\\\u041d\u043e\u0432\u0430\u044f \u043f\u0430\u043f\u043a\u0430\\2.mp3",
  "do u feel cold43214244535643532": "D:\\1Work\\Music\\\u043f\u0430\u043f\u043a\u0438 \u0441 \u0434\u0435\u043c\u043a\u0430\u043c\u0438\\\u041d\u043e\u0432\u0430\u044f \u043f\u0430\u043f\u043a\u0430\\do u feel cold43214244535643532.mp3",
  "fel cold mastering2222": "D:\\1Work\\Music\\\u043f\u0430\u043f\u043a\u0438 \u0441 \u0434\u0435\u043c\u043a\u0430\u043c\u0438\\\u041d\u043e\u0432\u0430\u044f \u043f\u0430\u043f\u043a\u0430\\fel cold mastering2222.mp3",
  "fel cold masteringfdsfdsfds": "D:\\1Work\\Music\\\u043f\u0430\u043f\u043a\u0438 \u0441 \u0434\u0435\u043c\u043a\u0430\u043c\u0438\\\u041d\u043e\u0432\u0430\u044f \u043f\u0430\u043f\u043a\u0430\\fel cold masteringfdsfdsfds.mp3",
  "math s1": "D:\\1Work\\Music\\\u0440\u0435\u043a\u0438\\math s1.mp3",
  "math s2": "D:\\1Work\\Music\\\u0440\u0435\u043a\u0438\\math s2.mp3",
  "math s3": "D:\\1Work\\Music\\\u0440\u0435\u043a\u0438\\math s3.mp3",
  "midwest jam": "D:\\1Work\\Music\\\u0440\u0435\u043a\u0438\\midwest jam.mp3",
  "_wav": "D:\\1Work\\Music\\\u0440\u0435\u043a\u0438\\_wav.mp3",
  "\u0430 \u044f \u0432\u0438": "D:\\1Work\\Music\\\u0440\u0435\u043a\u0438\\\u041d\u0435\u0441\u0438\u043a\\\u0430 \u044f \u0432\u0438.mp3",
  "\u0430 \u044f \u0432\u0438\u0434\u0435\u043b \u0430\u0439\u0444\u043e\u043d": "D:\\1Work\\Music\\\u0440\u0435\u043a\u0438\\\u041d\u0435\u0441\u0438\u043a\\\u0430 \u044f \u0432\u0438\u0434\u0435\u043b \u0430\u0439\u0444\u043e\u043d.mp3",
  "\u0432 \u044f\u043d\u0432\u0430\u0440\u0435 \u043b\u043e\u0445": "D:\\1Work\\Music\\\u0440\u0435\u043a\u0438\\\u041d\u0435\u0441\u0438\u043a\\\u0432 \u044f\u043d\u0432\u0430\u0440\u0435 \u043b\u043e\u0445.mp3",
  "\u0433\u0443\u0441\u0438 \u043d\u0435 \u043b\u0435\u0442\u0430\u044e\u0442 \u043d\u0430 \u044e\u0433": "D:\\1Work\\Music\\\u0440\u0435\u043a\u0438\\\u041d\u0435\u0441\u0438\u043a\\\u0433\u0443\u0441\u0438 \u043d\u0435 \u043b\u0435\u0442\u0430\u044e\u0442 \u043d\u0430 \u044e\u0433.mp3",
  "\u043a\u0430\u043a \u0433\u043e\u043f\u0430\u0447\u043e\u043a": "D:\\1Work\\Music\\\u0440\u0435\u043a\u0438\\\u041d\u0435\u0441\u0438\u043a\\\u043a\u0430\u043a \u0433\u043e\u043f\u0430\u0447\u043e\u043a.mp3",
  "\u043b\u0443\u043a \u043c\u0441\u0442\u0438\u0442": "D:\\1Work\\Music\\\u0440\u0435\u043a\u0438\\\u041d\u0435\u0441\u0438\u043a\\\u043b\u0443\u043a \u043c\u0441\u0442\u0438\u0442.mp3",
  "\u043d\u0435 \u0434\u0430\u0448\u0430 \u043d\u0435 \u043c\u0430\u0448\u0430": "D:\\1Work\\Music\\\u0440\u0435\u043a\u0438\\\u041d\u0435\u0441\u0438\u043a\\\u043d\u0435 \u0434\u0430\u0448\u0430 \u043d\u0435 \u043c\u0430\u0448\u0430.mp3",
  "\u043d\u0435 \u0434\u043e\u0432\u0435\u0440\u044f\u0439 \u0434\u0440\u0443\u0437\u044c\u044f\u043c": "D:\\1Work\\Music\\\u0440\u0435\u043a\u0438\\\u041d\u0435\u0441\u0438\u043a\\\u043d\u0435 \u0434\u043e\u0432\u0435\u0440\u044f\u0439 \u0434\u0440\u0443\u0437\u044c\u044f\u043c.mp3",
  "\u043e": "D:\\1Work\\Music\\\u0440\u0435\u043a\u0438\\\u041d\u0435\u0441\u0438\u043a\\\u043e.mp3",
  "\u0441\u043c\u044b\u0441\u043b \u0432 \u043e\u0432\u043e\u0449\u0430\u0445": "D:\\1Work\\Music\\\u0440\u0435\u043a\u0438\\\u041d\u0435\u0441\u0438\u043a\\\u0441\u043c\u044b\u0441\u043b \u0432 \u043e\u0432\u043e\u0449\u0430\u0445.mp3",
  "\u0441\u043e\u0431\u0430\u0447\u043a\u0430 \u0443\u0431\u044c\u0435\u0442": "D:\\1Work\\Music\\\u0440\u0435\u043a\u0438\\\u041d\u0435\u0441\u0438\u043a\\\u0441\u043e\u0431\u0430\u0447\u043a\u0430 \u0443\u0431\u044c\u0435\u0442.mp3",
  "\u0422\u0435\u043a\u0441\u0442 \u0414\u0435\u0440": "D:\\1Work\\Music\\\u0440\u0435\u043a\u0438\\\u041d\u0435\u0441\u0438\u043a\\\u0422\u0435\u043a\u0441\u0442 \u0414\u0435\u0440.mp3",
  "\u0445\u0430!": "D:\\1Work\\Music\\\u0440\u0435\u043a\u0438\\\u041d\u0435\u0441\u0438\u043a\\\u0445\u0430!.mp3",
  "\u0445\u0430": "D:\\1Work\\Music\\\u0440\u0435\u043a\u0438\\\u041d\u0435\u0441\u0438\u043a\\\u0445\u0430.mp3",
  "\u0445\u0430\u043d \u0441\u043e\u043b\u043e": "D:\\1Work\\Music\\\u0440\u0435\u043a\u0438\\\u041d\u0435\u0441\u0438\u043a\\\u0445\u0430\u043d \u0441\u043e\u043b\u043e.mp3",
  "\u0445\u043e\u043c\u044f\u043a\u0438 \u0431\u0430\u0431\u0443\u0448\u043a\u0435": "D:\\1Work\\Music\\\u0440\u0435\u043a\u0438\\\u041d\u0435\u0441\u0438\u043a\\\u0445\u043e\u043c\u044f\u043a\u0438 \u0431\u0430\u0431\u0443\u0448\u043a\u0435.mp3",
  "\u044f \u0442\u0432\u043e\u044e \u043c\u0430\u043c\u043a\u0443 \u043b\u044e\u0431\u043b\u044e": "D:\\1Work\\Music\\\u0440\u0435\u043a\u0438\\\u041d\u0435\u0441\u0438\u043a\\\u044f \u0442\u0432\u043e\u044e \u043c\u0430\u043c\u043a\u0443 \u043b\u044e\u0431\u043b\u044e.mp3",
  "How to cope with anxiety  Olivia Remes  TEDxUHasselt": "D:\\1Work\\trash\\How to cope with anxiety  Olivia Remes  TEDxUHasselt.mp3",
  "Lana Del Rey - Ultraviolence (Acapella)": "D:\\1Work\\trash\\Lana Del Rey - Ultraviolence (Acapella).mp3",
  "Whitney Houston Speaking Voice Through The Years (1984-2012)": "D:\\1Work\\trash\\Whitney Houston Speaking Voice Through The Years (1984-2012).mp3",
  "dead girl in the pool": "D:\\1Work\\\u043a\u0430\u0432\u0435\u0440\u044b\\dead girl in the pool.mp3",
  "splwlk": "D:\\1Work\\\u043a\u0430\u0432\u0435\u0440\u044b\\splwlk.mp3",
  "Adam Van Baker Sylenth1 Soundset Part 2": "D:\\Plugins\\Presets\\Banks\\Adam Van Baker Sylenth1 Soundset Part 2-3\\Adam Van Baker Sylenth1 Soundset Part 2\\Adam Van Baker Sylenth1 Soundset Part 2.mp3",
  "Adam Van Baker Sylenth1 Soundset Part 3": "D:\\Plugins\\Presets\\Banks\\Adam Van Baker Sylenth1 Soundset Part 2-3\\Adam Van Baker Sylenth1 Soundset Part 3\\Adam Van Baker Sylenth1 Soundset Part 3.mp3",
  "Mike Time Entertainment SoundBanks Sylenth1 Vol 1": "D:\\Plugins\\Presets\\Banks\\Mike Time Entertainment SoundBanks Sylenth1 Vol 1\\Mike Time Entertainment SoundBanks Sylenth1 Vol 1.mp3",
  "Twisted UK Hardcore Demo": "D:\\Plugins\\Presets\\Banks\\Molgli's Twisted UK Hardcore Sylenth Soundbank\\Twisted UK Hardcore Demo.mp3",
  "Designed Sounds 4 - DEMO": "D:\\Plugins\\Presets\\Banks\\Party Design - Designed Sounds for Sylenth1 Vol 4\\Designed Sounds 4 - DEMO.mp3",
  "Resonance Sound - Electro House Vol": "D:\\Plugins\\Presets\\Banks\\Resonance Sound - Electro House Vol.1\\Resonance Sound - Electro House Vol.1.mp3",
  "Samplestar Sylenth1 Progressive House Presets": "D:\\Plugins\\Presets\\Banks\\Samplestar Sylenth1 Progressive House Presets\\Samplestar Sylenth1 Progressive House Presets.mp3",
  "Shockwave - Essential Patch vol 1 - Sylenth1": "D:\\Plugins\\Presets\\Banks\\Shockwave - Essential Patch vol 1\\Shockwave - Essential Patch vol 1 - Sylenth1.mp3",
  "SoundBanks Sylenth1 Vol": "D:\\Plugins\\Presets\\Banks\\SoundBanks Sylenth1 Vol.1\\SoundBanks Sylenth1 Vol.1.mp3",
  "Uneek Sounds - Sylenth1 Exotics": "D:\\Plugins\\Presets\\Banks\\Uneek Sounds - Sylenth1 Exotics\\Uneek Sounds - Sylenth1 Exotics.mp3",
  "Vengeance Sylenth Soundset Vol": "D:\\Plugins\\Presets\\Presets\\Vengeance Sylenth Soundset Vol.6 - Acid Drops Signature\\Vengeance Sylenth Soundset Vol.6 - Acid Drops Signature.mp3",
  "Sylenth Trilogy Vol 1 Dance And HandsUp": "D:\\Plugins\\Presets\\Banks\\Vengeance Sylenth Trilogy Vol 1 Dance And HandsUp\\Sylenth Trilogy Vol 1 Dance And HandsUp.mp3",
  "Sylenth Trilogy Vol 2 Trance": "D:\\Plugins\\Presets\\Banks\\Vengeance Sylenth Trilogy Vol 2 Trance\\Sylenth Trilogy Vol 2 Trance.mp3",
  "Sylenth Trilogy Vol 3 Electro And House": "D:\\Plugins\\Presets\\Banks\\Vengeance Sylenth Trilogy Vol 3 Electro And House\\Sylenth Trilogy Vol 3 Electro And House.mp3",
  "Sylenth Trilogy Vol 4 DeLeon Signature Set": "D:\\Plugins\\Presets\\Banks\\Vengeance Sylenth Trilogy Vol 4 DeLeon Signature Set\\Sylenth Trilogy Vol 4 DeLeon Signature Set.mp3",
  "Studio 54 Vol 1 Demo": "D:\\Plugins\\Presets\\Banks\\Wow! Records - Studio 54 Vol. 1\\Studio 54 Vol 1 Demo.mp3",
  "Uneek Sounds - Pads Atmospheres for Sylenth 1": "D:\\Plugins\\Presets\\Presets\\Uneek Sounds - Pads Atmospheres for Sylenth 1\\Uneek Sounds - Pads Atmospheres for Sylenth 1.mp3",
  "Uneek Sounds - Urban Legend": "D:\\Plugins\\Presets\\Presets\\Uneek Sounds - Urban Legend\\Uneek Sounds - Urban Legend.mp3",
  "Waveform Recordings - Sylenth1 Deep & Tech Presets": "D:\\Plugins\\Presets\\Presets\\Waveform Recordings - Sylenth1 Deep & Tech Presets\\Waveform Recordings - Sylenth1 Deep & Tech Presets.mp3",
  "132029__aldebarancw__tape-player-sounds": "D:\\Samples\\132029__aldebarancw__tape-player-sounds.mp3",
  "Ambient Rain Sounds  Sample Pack": "D:\\Samples\\Ambient Rain Sounds  Sample Pack.mp3",
  "flock-of-seagulls_daniel-simion": "D:\\Samples\\flock-of-seagulls_daniel-simion.mp3",
  "Ocean_Waves-Mike_Koenig-980635527": "D:\\Samples\\Ocean_Waves-Mike_Koenig-980635527.mp3",
  "tape-player-sounds": "D:\\Samples\\tape-player-sounds.mp3",
  "Thunder   Sound effect": "D:\\Samples\\Thunder   Sound effect.mp3",
  "Thunderstorm SOUND EFFECT": "D:\\Samples\\Thunderstorm SOUND EFFECT.mp3",
  "Vinyl-35-RPM-15-Min": "D:\\Samples\\Vinyl-35-RPM-15-Min.mp3",
  "Sincinaty_RawFL_Sample_03": "D:\\Soft\\FL20\\Data\\Patches\\Misc\\Used by demo projects\\Gimbal & Sinan + Futorial - RawFL\\Sincinaty_RawFL_Sample_03.mp3",
  "Sincinaty_RawFL_Sample_04": "D:\\Soft\\FL20\\Data\\Patches\\Misc\\Used by demo projects\\Gimbal & Sinan + Futorial - RawFL\\Sincinaty_RawFL_Sample_04.mp3",
  "FX3": "D:\\Soft\\FL20\\Data\\Patches\\Misc\\Used by demo projects\\Hanging On (remix)\\FX3.mp3",
  "Great SpringrevStereo": "D:\\Soft\\FL20\\Data\\Patches\\Misc\\Used by demo projects\\Sacco - Goldener Schnitt\\Great SpringrevStereo.mp3",
  "IMP Cave - Chamber": "D:\\Soft\\FL20\\Data\\Patches\\Misc\\Used by demo projects\\Sacco - Goldener Schnitt\\IMP Cave - Chamber.mp3",
  "LargePlate_2": "D:\\Soft\\FL20\\Data\\Patches\\Misc\\Used by demo projects\\Sacco - Goldener Schnitt\\LargePlate_2.mp3",
  "SmallStudioRoom_3": "D:\\Soft\\FL20\\Data\\Patches\\Misc\\Used by demo projects\\Sacco - Goldener Schnitt\\SmallStudioRoom_3.mp3",
  "untitled": "D:\\Soft\\FL20\\Plugins\\Fruity\\Effects\\Edison\\Data\\Samples\\untitled.mp3",
  "222222222": "D:\\Steam\\222222222.mp3",
  "01 - Marcin Przybylowicz - V": "D:\\Steam\\steamapps\\common\\Cyberpunk 2077\\BonusContent\\soundtrack\\mp3\\cd1\\01 - Marcin Przybylowicz - V.mp3",
  "02 - Paul Leonard-Morgan - Extraction Action": "D:\\Steam\\steamapps\\common\\Cyberpunk 2077\\BonusContent\\soundtrack\\mp3\\cd1\\02 - Paul Leonard-Morgan - Extraction Action.mp3",
  "03 - P": "D:\\Steam\\steamapps\\common\\Cyberpunk 2077\\BonusContent\\soundtrack\\mp3\\cd1\\03 - P.T. Adamczyk - The Rebel Path.mp3",
  "04 - Paul Leonard-Morgan - The Streets Are Long-Ass Gutters": "D:\\Steam\\steamapps\\common\\Cyberpunk 2077\\BonusContent\\soundtrack\\mp3\\cd1\\04 - Paul Leonard-Morgan - The Streets Are Long-Ass Gutters.mp3",
  "05 - P": "D:\\Steam\\steamapps\\common\\Cyberpunk 2077\\BonusContent\\soundtrack\\mp3\\cd1\\05 - P.T. Adamczyk - Outsider No More.mp3",
  "06 - Marcin Przybylowicz - Cloudy Day": "D:\\Steam\\steamapps\\common\\Cyberpunk 2077\\BonusContent\\soundtrack\\mp3\\cd1\\06 - Marcin Przybylowicz - Cloudy Day.mp3",
  "07 - Marcin Przybylowicz - Wushu Dolls": "D:\\Steam\\steamapps\\common\\Cyberpunk 2077\\BonusContent\\soundtrack\\mp3\\cd1\\07 - Marcin Przybylowicz - Wushu Dolls.mp3",
  "08 - P": "D:\\Steam\\steamapps\\common\\Cyberpunk 2077\\BonusContent\\soundtrack\\mp3\\cd1\\08 - P.T. Adamczyk - Scavenger Hunt.mp3",
  "09 - P": "D:\\Steam\\steamapps\\common\\Cyberpunk 2077\\BonusContent\\soundtrack\\mp3\\cd1\\09 - P.T. Adamczyk - \u041c\u0443\u0441\u043e\u0440\u0449\u0438\u043a\u0438.mp3",
  "10 - Marcin Przybylowicz - Close Probing": "D:\\Steam\\steamapps\\common\\Cyberpunk 2077\\BonusContent\\soundtrack\\mp3\\cd1\\10 - Marcin Przybylowicz - Close Probing.mp3",
  "11 - Paul Leonard-Morgan - There_s Gonna Be A Parade!": "D:\\Steam\\steamapps\\common\\Cyberpunk 2077\\BonusContent\\soundtrack\\mp3\\cd1\\11 - Paul Leonard-Morgan - There_s Gonna Be A Parade!.mp3",
  "12 - Paul Leonard-Morgan - Trouble Finds Trouble": "D:\\Steam\\steamapps\\common\\Cyberpunk 2077\\BonusContent\\soundtrack\\mp3\\cd1\\12 - Paul Leonard-Morgan - Trouble Finds Trouble.mp3",
  "13 - P": "D:\\Steam\\steamapps\\common\\Cyberpunk 2077\\BonusContent\\soundtrack\\mp3\\cd1\\13 - P.T. Adamczyk - You Shall Never Have To Forgive Me Again.mp3",
  "14 - P": "D:\\Steam\\steamapps\\common\\Cyberpunk 2077\\BonusContent\\soundtrack\\mp3\\cd2\\14 - P.T. Adamczyk - To Hell and Back.mp3",
  "15 - P": "D:\\Steam\\steamapps\\common\\Cyberpunk 2077\\BonusContent\\soundtrack\\mp3\\cd1\\15 - P.T. Adamczyk - The Heist.mp3",
  "16 - Marcin Przybylowicz - Streetfighters": "D:\\Steam\\steamapps\\common\\Cyberpunk 2077\\BonusContent\\soundtrack\\mp3\\cd1\\16 - Marcin Przybylowicz - Streetfighters.mp3",
  "17 - Marcin Przybylowicz - Patri(di)ots": "D:\\Steam\\steamapps\\common\\Cyberpunk 2077\\BonusContent\\soundtrack\\mp3\\cd1\\17 - Marcin Przybylowicz - Patri(di)ots.mp3",
  "18 - Paul Leonard-Morgan - Mining Minds": "D:\\Steam\\steamapps\\common\\Cyberpunk 2077\\BonusContent\\soundtrack\\mp3\\cd1\\18 - Paul Leonard-Morgan - Mining Minds.mp3",
  "19 - P": "D:\\Steam\\steamapps\\common\\Cyberpunk 2077\\BonusContent\\soundtrack\\mp3\\cd1\\19 - P.T. Adamczyk - Rite Of Passage.mp3",
  "01 - P": "D:\\Steam\\steamapps\\common\\Cyberpunk 2077\\BonusContent\\soundtrack\\mp3\\cd2\\01 - P.T. Adamczyk - The Voice In My Head.mp3",
  "02 - Marcin Przybylowicz - Modern Anthill": "D:\\Steam\\steamapps\\common\\Cyberpunk 2077\\BonusContent\\soundtrack\\mp3\\cd2\\02 - Marcin Przybylowicz - Modern Anthill.mp3",
  "03 - Paul Leonard-Morgan - The Sacred And The Profane": "D:\\Steam\\steamapps\\common\\Cyberpunk 2077\\BonusContent\\soundtrack\\mp3\\cd2\\03 - Paul Leonard-Morgan - The Sacred And The Profane.mp3",
  "04 - P": "D:\\Steam\\steamapps\\common\\Cyberpunk 2077\\BonusContent\\soundtrack\\mp3\\cd2\\04 - P.T. Adamczyk - Kang Tao Down.mp3",
  "05 - Marcin Przybylowicz - Cyberwildlife Park": "D:\\Steam\\steamapps\\common\\Cyberpunk 2077\\BonusContent\\soundtrack\\mp3\\cd2\\05 - Marcin Przybylowicz - Cyberwildlife Park.mp3",
  "06 - Marcin Przybylowicz - Consumer Cathedral": "D:\\Steam\\steamapps\\common\\Cyberpunk 2077\\BonusContent\\soundtrack\\mp3\\cd2\\06 - Marcin Przybylowicz - Consumer Cathedral.mp3",
  "07 - P": "D:\\Steam\\steamapps\\common\\Cyberpunk 2077\\BonusContent\\soundtrack\\mp3\\cd2\\07 - P.T. Adamczyk - Juiced Up.mp3",
  "08 - Paul Leonard-Morgan - Bells Of Laguna Bend": "D:\\Steam\\steamapps\\common\\Cyberpunk 2077\\BonusContent\\soundtrack\\mp3\\cd2\\08 - Paul Leonard-Morgan - Bells Of Laguna Bend.mp3",
  "09 - Marcin Przybylowicz - Urban Downunder": "D:\\Steam\\steamapps\\common\\Cyberpunk 2077\\BonusContent\\soundtrack\\mp3\\cd2\\09 - Marcin Przybylowicz - Urban Downunder.mp3",
  "10 - P": "D:\\Steam\\steamapps\\common\\Cyberpunk 2077\\BonusContent\\soundtrack\\mp3\\cd2\\10 - P.T. Adamczyk - Atlantis.mp3",
  "11 - Marcin Przybylowicz - Cyberninja": "D:\\Steam\\steamapps\\common\\Cyberpunk 2077\\BonusContent\\soundtrack\\mp3\\cd2\\11 - Marcin Przybylowicz - Cyberninja.mp3",
  "12 - Paul Leonard-Morgan - The Suits Are Scared": "D:\\Steam\\steamapps\\common\\Cyberpunk 2077\\BonusContent\\soundtrack\\mp3\\cd2\\12 - Paul Leonard-Morgan - The Suits Are Scared.mp3",
  "13 - Paul Leonard-Morgan - Tower Lockdown": "D:\\Steam\\steamapps\\common\\Cyberpunk 2077\\BonusContent\\soundtrack\\mp3\\cd2\\13 - Paul Leonard-Morgan - Tower Lockdown.mp3",
  "15 - Paul Leonard-Morgan - Adam Smasher": "D:\\Steam\\steamapps\\common\\Cyberpunk 2077\\BonusContent\\soundtrack\\mp3\\cd2\\15 - Paul Leonard-Morgan - Adam Smasher.mp3",
  "16 - Paul Leonard-Morgan - Hanako _ Yorinobu": "D:\\Steam\\steamapps\\common\\Cyberpunk 2077\\BonusContent\\soundtrack\\mp3\\cd2\\16 - Paul Leonard-Morgan - Hanako _ Yorinobu.mp3",
  "17 - Marcin Przybylowicz - Been Good To Know Ya": "D:\\Steam\\steamapps\\common\\Cyberpunk 2077\\BonusContent\\soundtrack\\mp3\\cd2\\17 - Marcin Przybylowicz - Been Good To Know Ya.mp3",
  "18 - P": "D:\\Steam\\steamapps\\common\\Cyberpunk 2077\\BonusContent\\soundtrack\\mp3\\cd2\\18 - P.T. Adamczyk - Never Fade Away (SAMURAI Cover) - feat. Olga Jankowska.mp3",
  "01 Quixotic (Scattle Remix)": "D:\\Steam\\steamapps\\common\\Hotline Miami 2\\Remix EP\\MP3\\01 Quixotic (Scattle Remix).mp3",
  "02 Dust (Carpenter Brut Remix)": "D:\\Steam\\steamapps\\common\\Hotline Miami 2\\Remix EP\\MP3\\02 Dust (Carpenter Brut Remix).mp3",
  "03 Bloodline (M_O_O_N's Extra Cheese Mix)": "D:\\Steam\\steamapps\\common\\Hotline Miami 2\\Remix EP\\MP3\\03 Bloodline (M_O_O_N's Extra Cheese Mix).mp3",
  "04 Roller Mobster (Scattle Remix)": "D:\\Steam\\steamapps\\common\\Hotline Miami 2\\Remix EP\\MP3\\04 Roller Mobster (Scattle Remix).mp3",
  "05 Le Perv (M_O_O_N Remix)": "D:\\Steam\\steamapps\\common\\Hotline Miami 2\\Remix EP\\MP3\\05 Le Perv (M_O_O_N Remix).mp3",
  "06 Remorse (Carpenter Brut Remix)": "D:\\Steam\\steamapps\\common\\Hotline Miami 2\\Remix EP\\MP3\\06 Remorse (Carpenter Brut Remix).mp3",
  "amb_bigfoot_backing_drone_01": "D:\\Steam\\tenfoot\\resource\\sounds\\ambient\\amb_bigfoot_backing_drone_01.mp3",
  "amb_bigfoot_backing_part_01_01": "D:\\Steam\\tenfoot\\resource\\sounds\\ambient\\amb_bigfoot_backing_part_01_01.mp3",
  "amb_bigfoot_backing_part_01_02": "D:\\Steam\\tenfoot\\resource\\sounds\\ambient\\amb_bigfoot_backing_part_01_02.mp3",
  "amb_bigfoot_backing_part_01_03": "D:\\Steam\\tenfoot\\resource\\sounds\\ambient\\amb_bigfoot_backing_part_01_03.mp3",
  "amb_bigfoot_backing_part_01_04": "D:\\Steam\\tenfoot\\resource\\sounds\\ambient\\amb_bigfoot_backing_part_01_04.mp3",
  "amb_bigfoot_backing_part_01_05": "D:\\Steam\\tenfoot\\resource\\sounds\\ambient\\amb_bigfoot_backing_part_01_05.mp3",
  "amb_bigfoot_backing_part_01_06": "D:\\Steam\\tenfoot\\resource\\sounds\\ambient\\amb_bigfoot_backing_part_01_06.mp3",
  "amb_bigfoot_backing_part_01_07": "D:\\Steam\\tenfoot\\resource\\sounds\\ambient\\amb_bigfoot_backing_part_01_07.mp3",
  "amb_bigfoot_backing_part_01_08": "D:\\Steam\\tenfoot\\resource\\sounds\\ambient\\amb_bigfoot_backing_part_01_08.mp3",
  "amb_bigfoot_backing_part_01_09": "D:\\Steam\\tenfoot\\resource\\sounds\\ambient\\amb_bigfoot_backing_part_01_09.mp3",
  "amb_bigfoot_backing_part_02_01": "D:\\Steam\\tenfoot\\resource\\sounds\\ambient\\amb_bigfoot_backing_part_02_01.mp3",
  "amb_bigfoot_backing_part_02_02": "D:\\Steam\\tenfoot\\resource\\sounds\\ambient\\amb_bigfoot_backing_part_02_02.mp3",
  "amb_bigfoot_backing_part_02_03": "D:\\Steam\\tenfoot\\resource\\sounds\\ambient\\amb_bigfoot_backing_part_02_03.mp3",
  "amb_bigfoot_backing_part_02_04": "D:\\Steam\\tenfoot\\resource\\sounds\\ambient\\amb_bigfoot_backing_part_02_04.mp3",
  "amb_bigfoot_backing_part_02_05": "D:\\Steam\\tenfoot\\resource\\sounds\\ambient\\amb_bigfoot_backing_part_02_05.mp3",
  "amb_bigfoot_backing_part_02_06": "D:\\Steam\\tenfoot\\resource\\sounds\\ambient\\amb_bigfoot_backing_part_02_06.mp3",
  "amb_bigfoot_backing_part_02_07": "D:\\Steam\\tenfoot\\resource\\sounds\\ambient\\amb_bigfoot_backing_part_02_07.mp3",
  "amb_bigfoot_backing_part_02_08": "D:\\Steam\\tenfoot\\resource\\sounds\\ambient\\amb_bigfoot_backing_part_02_08.mp3",
  "amb_bigfoot_backing_part_02_09": "D:\\Steam\\tenfoot\\resource\\sounds\\ambient\\amb_bigfoot_backing_part_02_09.mp3",
  "amb_bigfoot_backing_part_03_01": "D:\\Steam\\tenfoot\\resource\\sounds\\ambient\\amb_bigfoot_backing_part_03_01.mp3",
  "amb_bigfoot_backing_part_03_02": "D:\\Steam\\tenfoot\\resource\\sounds\\ambient\\amb_bigfoot_backing_part_03_02.mp3",
  "amb_bigfoot_backing_part_03_03": "D:\\Steam\\tenfoot\\resource\\sounds\\ambient\\amb_bigfoot_backing_part_03_03.mp3",
  "amb_bigfoot_backing_part_03_04": "D:\\Steam\\tenfoot\\resource\\sounds\\ambient\\amb_bigfoot_backing_part_03_04.mp3",
  "amb_bigfoot_backing_part_03_05": "D:\\Steam\\tenfoot\\resource\\sounds\\ambient\\amb_bigfoot_backing_part_03_05.mp3",
  "amb_bigfoot_backing_part_03_06": "D:\\Steam\\tenfoot\\resource\\sounds\\ambient\\amb_bigfoot_backing_part_03_06.mp3",
  "amb_bigfoot_backing_part_03_07": "D:\\Steam\\tenfoot\\resource\\sounds\\ambient\\amb_bigfoot_backing_part_03_07.mp3",
  "amb_bigfoot_backing_part_03_08": "D:\\Steam\\tenfoot\\resource\\sounds\\ambient\\amb_bigfoot_backing_part_03_08.mp3",
  "amb_bigfoot_backing_part_03_09": "D:\\Steam\\tenfoot\\resource\\sounds\\ambient\\amb_bigfoot_backing_part_03_09.mp3",
  "happy bd": "D:\\studia\\poprzednie semestry\\jebanutyisajt\\happy bd.mp3",
  "potterflute": "D:\\studia\\poprzednie semestry\\jebanutyisajt\\potterflute.mp3",
  "titanflute": "D:\\studia\\poprzednie semestry\\jebanutyisajt\\titanflute.mp3",
  "house_lo": "D:\\studia\\poprzednie semestry\\PycharmProjects\\raspberry\\venv\\Lib\\site-packages\\pygame\\examples\\data\\house_lo.mp3",
  "alnk": "D:\\Web projects\\otwal\\audio\\alnk.mp3",
  "intro": "D:\\Web projects\\otwal\\audio\\intro.mp3",
  "nezhno": "D:\\Web projects\\otwal\\audio\\nezhno.mp3",
  "noliz10": "D:\\Web projects\\otwal\\audio\\noliz10.mp3",
  "popularen": "D:\\Web projects\\otwal\\audio\\popularen.mp3",
  "warning": "D:\\Web projects\\otwal\\audio\\warning.mp3"
}